tests/__init__.py
tests/test_WaterQuality.py
waterquality/Common.py
waterquality/WaterQuality.ini
waterquality/WaterQuality.py
waterquality/__init__.py
waterquality/inversion_functions.py
waterquality-1.1.5.dist-info/LICENSE
waterquality-1.1.5.dist-info/METADATA
waterquality-1.1.5.dist-info/WHEEL
waterquality-1.1.5.dist-info/entry_points.txt
waterquality-1.1.5.dist-info/top_level.txt
waterquality-1.1.5.dist-info/RECORD
